{
    "results": {},
    "season": {
        "5ucfHYcseSSyP1mYz8q1OYA2JX83": 0,
        "7QSsNsOFhDaOlYC5Cdp0syqGHye2": 0,
        "A58m9S6zZbgsdWWNenbmiyb2XYV2": 0,
        "EnlBfJUDCPNqfRmvUKSV4Mwc2Kp2": 0,
        "Hz2ymiE3tEMtFZGvrnOVWnGSDxh1": 0,
        "ILpqN71uWYgntnyHKmoMCnDEvHX2": 0,
        "IXCpj22XLIN2v2ErOT4b3SfvfgY2": 0,
        "MQYzCr1cCVPfDRozApEjOm1GrS32": 0,
        "QoO2qioczwZiKmTPN0Ouc9d41Gp2": 0,
        "RU6TaRlkzrbFuiUZGZQwZxKilP62": 0,
        "XjdOgIfHf7OjqxwWJZ1EUkHDiaM2": 0,
        "ZhLut25YyRY7YI5wsaVPa82NbGi1": 0,
        "cWuecaLlegW3JBUHCe2pRgdUOUX2": 0,
        "exo6jPZWIngkxB7FUFfUwTGtSun2": 0,
        "himC4gtBOXarAUFYBPYkmgkqvYa2": 0,
        "k0HzhSYwuONEoDkl3idlCRu8hp82": 0,
        "u2R63YO0ZlNzd19jKaGtw1RPuQ53": 0,
        "uPOnDjHqFGUiovg6l9REpHW37zD3": 0,
        "uucJKVuMAIQpHBmaOLecsMtQTdK2": 0,
        "yJV8gAryvudiyFOMBUa4ChcPXrt1": 0,
        "ysvTSr8XBxd3pGuE0AFLH6rRkj53": 0
    },
    "users": {
        "1ocBU2rjs8Xsw12dCYuAMGbFjBj2": {
            "ddd": "philbuch",
            "name": "Phil Buch"
        },
        "5ucfHYcseSSyP1mYz8q1OYA2JX83": {
            "ddd": "r@vine8085",
            "name": "Ken Nelson "
        },
        "7QSsNsOFhDaOlYC5Cdp0syqGHye2": {
            "name": "Jamie Stuenkel"
        },
        "A58m9S6zZbgsdWWNenbmiyb2XYV2": {
            "ddd": "karenk",
            "name": "Karen Keller "
        },
        "EnlBfJUDCPNqfRmvUKSV4Mwc2Kp2": {
            "ddd": "jubneh-qezsyf-Kyzsu5",
            "name": "Jason Clayton "
        },
        "Hz2ymiE3tEMtFZGvrnOVWnGSDxh1": {
            "ddd": "LowerB72",
            "name": "Dorothy Fowler "
        },
        "ILpqN71uWYgntnyHKmoMCnDEvHX2": {
            "ddd": "Kickoff!",
            "name": "Donna Aynesworth "
        },
        "IXCpj22XLIN2v2ErOT4b3SfvfgY2": {
            "ddd": "trovata2014",
            "name": "Stephen Benedict "
        },
        "MQYzCr1cCVPfDRozApEjOm1GrS32": {
            "ddd": "05Petr23",
            "name": "Scott Petersen "
        },
        "QoO2qioczwZiKmTPN0Ouc9d41Gp2": {
            "name": "Jeff Stuenkel "
        },
        "RU6TaRlkzrbFuiUZGZQwZxKilP62": {
            "ddd": "justin41",
            "name": "Justin Taylor "
        },
        "XjdOgIfHf7OjqxwWJZ1EUkHDiaM2": {
            "name": "Brandon Rogers"
        },
        "ZhLut25YyRY7YI5wsaVPa82NbGi1": {
            "ddd": "Tigerlsu1!",
            "name": "Bob Borron "
        },
        "exo6jPZWIngkxB7FUFfUwTGtSun2": {
            "ddd": "MoneyBags61",
            "name": "Steven Fekete "
        },
        "himC4gtBOXarAUFYBPYkmgkqvYa2": {
            "name": "Matthew Plaisance"
        },
        "uPOnDjHqFGUiovg6l9REpHW37zD3": {
            "ddd": "Nelson12",
            "name": "Lauren Wadman "
        },
        "uucJKVuMAIQpHBmaOLecsMtQTdK2": {
            "name": "Travis Wadman "
        },
        "yJV8gAryvudiyFOMBUa4ChcPXrt1": {
            "name": "Ken Tooke"
        },
        "ysvTSr8XBxd3pGuE0AFLH6rRkj53": {
            "ddd": "Campbell0821$",
            "name": "Brady Stuenkel "
        }
    }
}